scine_sparrow/LICENSE.txt
scine_sparrow/__init__.py
scine_sparrow/libutilsos.so
scine_sparrow/sparrow.module.so
scine_sparrow.libs/libboost_atomic-00e6ede8.so.1.78.0
scine_sparrow.libs/libboost_filesystem-e9e1d9ac.so.1.78.0
scine_sparrow.libs/libboost_system-c0fa27da.so.1.78.0
scine_sparrow.libs/libcore-6a155538.so
scine_sparrow.libs/libgomp-e985bcbb.so.1.0.0
scine_sparrow.libs/libutilsos-1a1c26a4.so
scine_sparrow-5.2.0.dist-info/METADATA
scine_sparrow-5.2.0.dist-info/WHEEL
scine_sparrow-5.2.0.dist-info/top_level.txt
scine_sparrow-5.2.0.dist-info/RECORD
